efficient_pruners/__init__.py
efficient_pruners/__version__.py
efficient_pruners/config.py
efficient_pruners/core.py
efficient_pruners/__pycache__/__init__.cpython-312.pyc
efficient_pruners/__pycache__/__version__.cpython-312.pyc
efficient_pruners/__pycache__/config.cpython-312.pyc
efficient_pruners/__pycache__/core.cpython-312.pyc
efficient_pruners/models/__init__.py
efficient_pruners/models/sparsity_predictor.py
efficient_pruners/models/__pycache__/__init__.cpython-312.pyc
efficient_pruners/models/__pycache__/sparsity_predictor.cpython-312.pyc
efficient_pruners/utils/__init__.py
efficient_pruners/utils/model_utils.py
efficient_pruners/utils/reward_utils.py
efficient_pruners/utils/__pycache__/__init__.cpython-312.pyc
efficient_pruners/utils/__pycache__/model_utils.cpython-312.pyc
efficient_pruners/utils/__pycache__/reward_utils.cpython-312.pyc
efficient_pruners-0.1.0.dist-info/licenses/LICENSE
efficient_pruners-0.1.0.dist-info/METADATA
efficient_pruners-0.1.0.dist-info/WHEEL
efficient_pruners-0.1.0.dist-info/top_level.txt
efficient_pruners-0.1.0.dist-info/RECORD
