Metadata-Version: 2.4
Name: efficient_pruners
Version: 0.1.0
Summary: Calibration-Free Model Compression with Reinforcement Learning-Based Policy Learning
Home-page: https://github.com/parmanu-lcs2/efficient_pruners
Author: Parmanu, LCS2, IIT Delhi
Author-email: 
License: MIT
Project-URL: Homepage, https://github.com/parmanu-lcs2/efficient_pruners
Project-URL: Bug Reports, https://github.com/parmanu-lcs2/efficient_pruners/issues
Project-URL: Source, https://github.com/parmanu-lcs2/efficient_pruners
Keywords: model-compression,pruning,reinforcement-learning,transformers,llm,deep-learning,pytorch
Classifier: Development Status :: 3 - Alpha
Classifier: Intended Audience :: Developers
Classifier: Intended Audience :: Science/Research
Classifier: License :: OSI Approved :: MIT License
Classifier: Programming Language :: Python :: 3
Classifier: Programming Language :: Python :: 3.8
Classifier: Programming Language :: Python :: 3.9
Classifier: Programming Language :: Python :: 3.10
Classifier: Programming Language :: Python :: 3.11
Classifier: Topic :: Scientific/Engineering :: Artificial Intelligence
Requires-Python: >=3.8
License-File: LICENSE
Requires-Dist: torch>=1.12.0
Requires-Dist: transformers>=4.30.0
Requires-Dist: numpy>=1.23.0
Requires-Dist: scipy>=1.9.0
Requires-Dist: tqdm>=4.65.0
Provides-Extra: dev
Requires-Dist: pytest>=7.0.0; extra == "dev"
Requires-Dist: black>=22.0.0; extra == "dev"
Requires-Dist: flake8>=4.0.0; extra == "dev"
Requires-Dist: jupyter>=1.0.0; extra == "dev"
Provides-Extra: eval
Requires-Dist: lm-eval>=0.4.0; extra == "eval"
Requires-Dist: datasets>=2.10.0; extra == "eval"
Requires-Dist: evaluate>=0.4.0; extra == "eval"
Provides-Extra: finetune
Requires-Dist: peft>=0.5.0; extra == "finetune"
Requires-Dist: pytorch-lightning>=2.0.0; extra == "finetune"
Provides-Extra: logging
Requires-Dist: wandb>=0.15.0; extra == "logging"
Requires-Dist: tensorboard>=2.11.0; extra == "logging"
Provides-Extra: all
Requires-Dist: lm-eval>=0.4.0; extra == "all"
Requires-Dist: datasets>=2.10.0; extra == "all"
Requires-Dist: evaluate>=0.4.0; extra == "all"
Requires-Dist: peft>=0.5.0; extra == "all"
Requires-Dist: pytorch-lightning>=2.0.0; extra == "all"
Requires-Dist: wandb>=0.15.0; extra == "all"
Requires-Dist: tensorboard>=2.11.0; extra == "all"
Dynamic: home-page
Dynamic: license-file
Dynamic: requires-python
